hello_app/__init__.py
hello_app/hello.py
hello_app-0.1.1.dist-info/METADATA
hello_app-0.1.1.dist-info/WHEEL
hello_app-0.1.1.dist-info/top_level.txt
hello_app-0.1.1.dist-info/RECORD
