Metadata-Version: 2.1
Name: hello_app
Version: 0.1.1
Summary: A simple hello world app
Author: Curtis
Provides-Extra: test
Requires-Dist: pytest ; extra == 'test'
